tcrpy/__init__.py
tcrpy/__main__.py
tcrpy/api.py
tcrpy/auth.py
tcrpy/enums.py
tcrpy/models.py
tcrpy/utils.py
tcrpy-0.2.9.1.dist-info/LICENSE
tcrpy-0.2.9.1.dist-info/METADATA
tcrpy-0.2.9.1.dist-info/WHEEL
tcrpy-0.2.9.1.dist-info/top_level.txt
tcrpy-0.2.9.1.dist-info/RECORD
