Metadata-Version: 2.1
Name: tcrpy
Version: 0.2.9.1
Summary: A Python Library for Interacting with the TCR Platform API.
Home-page: https://github.com/mitchellaha/tcrpy
Author: Mitch V Aureli
Author-email: mitch@logic3ii.com
Classifier: Programming Language :: Python :: 3
Classifier: License :: OSI Approved :: MIT License
Classifier: Operating System :: OS Independent
Requires-Python: >=3.6
License-File: LICENSE
Requires-Dist: beautifulsoup4 (==4.11.1)
Requires-Dist: pydantic (==1.9.0)
Requires-Dist: python-dotenv (==0.20.0)
Requires-Dist: requests (==2.27.1)
